gitlabfs/cache.py
gitlabfs/filesystem.py
gitlabfs/resolver.py
gitlabfs-1.1.0.data/scripts/glfs
gitlabfs-1.1.0.dist-info/LICENSE
gitlabfs-1.1.0.dist-info/METADATA
gitlabfs-1.1.0.dist-info/WHEEL
gitlabfs-1.1.0.dist-info/top_level.txt
gitlabfs-1.1.0.dist-info/RECORD
