Metadata-Version: 2.1
Name: gitlabfs
Version: 1.1.0
Summary: Mount projects in GitLab as a file system
Home-page: https://github.com/Overv/gitlabfs
Author: Alexander Overvoorde
Author-email: overv161@gmail.com
License: UNKNOWN
Platform: UNKNOWN
Classifier: Programming Language :: Python :: 3.5
Classifier: License :: OSI Approved :: MIT License
Classifier: Operating System :: POSIX :: Linux
Requires-Python: >=3.5
Requires-Dist: python-gitlab
Requires-Dist: fusepy
Requires-Dist: iso8601
Requires-Dist: cachetools
